{
    "arrangers": [],
    "attributed_composers": [
        "Josquin des Prez"
    ],
    "composer_s_dates": [
        "~1450-1521/08/27"
    ],
    "composers": [],
    "digital_editors": [
        "Jesse Rodin"
    ],
    "distributors": [],
    "editors": [],
    "electronic_edition_versions": [
        "2012/06/20"
    ],
    "encoders": [
        "Chris Gage 06-07-2012"
    ],
    "encoding_applications": [
        {
            "date": "2023-01-24T21:53:49",
            "applicationVersion": "3.15.0-dev-5260bd2-dirty",
            "applicationName": {
                "value": "Verovio"
            },
            "note": "Transcoded from Humdrum"
        }
    ],
    "encoding_dates": [
        "None"
    ],
    "encoding_dates_of_the_electronic_document": [
        "2012/06/07"
    ],
    "genres": [
        "Chanson"
    ],
    "lyricists": [],
    "manuscript_sources_names": [],
    "movement_designation": [],
    "nota_bene": [
        "Translated from MusicXML and edited on 2012/06/20/ by Craig Sapp"
    ],
    "number": [],
    "project_description": [
        "Encoded by: Chris Gage 06-07-2012",
        "Version: 2012/06/20/"
    ],
    "rdfkern": [
        "l=long note in original notation",
        "i=editorial accidental",
        "V=start of tuplet marker",
        "Z=end of tuplet marker"
    ],
    "scholarly_catalogues": [
        "New Josquin Edition 30.17"
    ],
    "scholarly_catalogues_abbreviation_and_number": [
        "NJE 30.17"
    ],
    "subordinate_titles": [],
    "system_decoration": [],
    "title_of_larger_work": [],
    "titles": [
        "Il n'est plaisir"
    ],
    "voices": [
        "3"
    ],
    "voices_opr": []
}