{
    "score_uri": "https://raw.githubusercontent.com/polifonia-project/tonalities_pilot/main/scores/Willaert/Willaert_Praeter_rerum_seriem.mei",
    "attributed_composers": [],
    "composer_s_dates": [],
    "composers": [
        "Adrian Willaert"
    ],
    "digital_editors": [],
    "distributors": [],
    "editors": [
        "Marco Gurrieri (IReMus)",
        "Pothárn Imre (ChoralWiki)"
    ],
    "electronic_edition_versions": [],
    "encoders": [],
    "encoding_applications": [
        {
            "date": "2023-10-31T15:42:39",
            "applicationVersion": "4.1.0-dev-00c6c9c",
            "applicationName": {
                "value": "Verovio"
            },
            "note": "Transcoded from MusicXML"
        }
    ],
    "encoding_dates": [
        "2023-10-30 00:00:00"
    ],
    "encoding_dates_of_the_electronic_document": [],
    "genres": [],
    "lyricists": [],
    "manuscript_sources_names": [],
    "movement_designation": [],
    "nota_bene": [],
    "number": [],
    "project_description": [],
    "rdfkern": [],
    "scholarly_catalogues": [],
    "scholarly_catalogues_abbreviation_and_number": [],
    "subordinate_titles": [],
    "system_decoration": [],
    "title_of_larger_work": [],
    "titles": [
        "Praeter rerum seriem"
    ],
    "voices": [],
    "voices_opr": []
}